cache_middleware/__init__.py
cache_middleware/decorators.py
cache_middleware/helpers.py
cache_middleware/logger_config.py
cache_middleware/middleware.py
cache_middleware/backends/__init__.py
cache_middleware/backends/memcached_backend.py
cache_middleware/backends/memory_backend.py
cache_middleware/backends/redis_backend.py
cache_middleware-0.1.6.dist-info/METADATA
cache_middleware-0.1.6.dist-info/WHEEL
cache_middleware-0.1.6.dist-info/licenses/LICENSE
cache_middleware-0.1.6.dist-info/RECORD
