Metadata-Version: 2.4
Name: cache-middleware
Version: 0.1.6
Summary: Cache capabilities middleware for Starlette/Fastapi
Author-email: Linus <impalah@gmail.com>
License: MIT
License-File: LICENSE
Keywords: cache,fastapi,middleware,starlette
Classifier: Development Status :: 4 - Beta
Classifier: Framework :: FastAPI
Classifier: Intended Audience :: Developers
Classifier: License :: OSI Approved :: MIT License
Classifier: Programming Language :: Python :: 3
Classifier: Topic :: Software Development :: Libraries :: Python Modules
Classifier: Topic :: System :: Distributed Computing
Requires-Python: >=3.12
Requires-Dist: fastapi>=0.116.1
Requires-Dist: loguru>=0.7.3
Requires-Dist: svix-ksuid>=0.6.2
Requires-Dist: tenacity>=9.1.2
Requires-Dist: uvicorn>=0.35.0
Provides-Extra: all
Requires-Dist: aiomcache>=0.8.2; extra == 'all'
Requires-Dist: redis[hiredis]>=6.2.0; extra == 'all'
Provides-Extra: memcached
Requires-Dist: aiomcache>=0.8.2; extra == 'memcached'
Provides-Extra: redis
Requires-Dist: redis[hiredis]>=6.2.0; extra == 'redis'
